{
  "slug": "illeven-eleven",
  "name": "Illeven Eleven",
  "country": "USA",
  "founded_year": 2004,
  "description_en": "Illeven Eleven is a Chicago breakbeat label associated with the US breaks continuum that ran from Florida electro-funk revivalism into heavier club-focused bass music. In scene terms, it sits in the lane of labels that kept American breakbeat active through the 2000s and beyond, with a catalogue built for DJs rather than crossover branding.\n\nAvailable sources consistently place the label in Chicago and connect its launch to the mid-2000s. A 2004 foundation date appears in industry-facing material, while the label's own profile frames 2005 as the point from which it became a dedicated home for breakbeat. Taken together, that suggests an early-to-mid-2000s start and a clear identity formed around the US breaks circuit.\n\nIts editorial line is rooted in breakbeat, but not in a narrow sense. Illeven Eleven has also moved through bass music, electro-leaning club tracks and adjacent sounds that fit North American DJ culture, especially the strand where breaks, party-rocking vocals and low-end pressure coexist.\n\nThe label is strongly linked with Keith Mackenzie, one of the most recognisable names in US breakbeat, and with artists from the same orbit such as DJ Fixx, Sporty-O and Whiskey Pete. Those associations place it inside a practical network of producers and DJs who helped sustain the sound in clubs, on specialist radio and in digital stores after the peak years of physical breaks distribution.\n\nRather than being defined by one canonical release series alone, Illeven Eleven seems to have functioned as a reliable outlet for singles, remixes and club tools. That matters in breakbeat history: many labels in the style were less about album-era narratives than about keeping DJs supplied with new rollers, vocal cuts and peak-time material.\n\nIts catalogue is commonly described as breakbeat-first, but the surrounding ecosystem includes drum & bass, dubstep and bass-heavy crossover traffic. That does not make it a genre-neutral imprint; instead, it reflects how US breaks labels often operated in conversation with neighbouring scenes while still maintaining a recognisable rhythmic identity.\n\nChicago is an important part of the story. Although American breakbeat is often narrated through Florida, West Coast electro or broader EDM channels, Illeven Eleven shows how the sound also had durable infrastructure in other cities. In that sense, the label belongs to a wider map of regional scenes connected by touring DJs, online shops and digital distribution.\n\nThe label's continued online presence suggests an imprint that has remained active in some editorial sense, even as the market shifted from vinyl-led specialist culture to download platforms and streaming-era visibility. Its presence on platforms such as SoundCloud, Beatport and social media fits that transition from classic breaks label model to a more flexible digital-era operation.\n\nFor Optimal Breaks, Illeven Eleven is notable less as a mythologised institution than as a working scene label: one of the imprints that helped keep US breakbeat circulating after the genre's commercial high-water mark. Its value lies in continuity, DJ utility and its connection to artists who remained committed to the form.\n\nThat makes Illeven Eleven a useful reference point for understanding post-2000 American breakbeat culture: regional but connected, stylistically focused but open to adjacent bass forms, and built around the practical needs of club music rather than prestige narratives.",
  "description_es": "Illeven Eleven es un sello de breakbeat de Chicago asociado al continuo del breaks estadounidense que fue del revival electro-funk de Florida hacia formas de bass music más duras y orientadas al club. Dentro de la escena, ocupa el espacio de los sellos que mantuvieron vivo el breakbeat americano durante los años 2000 y después, con un catálogo pensado para DJs más que para una lógica de marca crossover.\n\nLas fuentes disponibles sitúan de forma consistente al sello en Chicago y vinculan su arranque a mediados de los 2000. En material de perfil industrial aparece 2004 como año de fundación, mientras que la propia presentación del sello habla de 2005 como el momento en que se consolidó como refugio específico para el breakbeat. En conjunto, eso apunta a un inicio de principios o mediados de esa década y a una identidad claramente formada alrededor del circuito US breaks.\n\nSu línea editorial está enraizada en el breakbeat, pero no en un sentido estrecho. Illeven Eleven también se ha movido por terrenos de bass music, tracks de club con sesgo electro y sonidos vecinos que encajan en la cultura DJ norteamericana, especialmente en esa franja donde conviven breaks, voces de impacto festivo y presión de graves.\n\nEl sello está fuertemente ligado a Keith Mackenzie, uno de los nombres más reconocibles del breakbeat estadounidense, y a artistas de la misma órbita como DJ Fixx, Sporty-O y Whiskey Pete. Esas asociaciones lo sitúan dentro de una red práctica de productores y DJs que ayudó a sostener el sonido en clubes, radios especializadas y tiendas digitales tras los años de mayor peso del formato físico.\n\nMás que definirse por una única serie canónica de referencias, Illeven Eleven parece haber funcionado como una plataforma fiable para singles, remixes y herramientas de club. Eso es importante en la historia del breakbeat: muchos sellos del estilo no se articularon tanto alrededor de una narrativa de álbumes como de la necesidad de abastecer a los DJs con nuevos rollers, cortes vocales y material de hora punta.\n\nSu catálogo suele describirse como centrado en breakbeat, pero el ecosistema que lo rodea incluye drum & bass, dubstep y cruces de bass music. Eso no lo convierte en un imprint sin perfil de género; más bien refleja cómo muchos sellos estadounidenses de breaks operaban en conversación con escenas vecinas sin perder una identidad rítmica reconocible.\n\nChicago es una parte importante de la historia. Aunque el relato del breakbeat americano suele pasar por Florida, la costa oeste o canales más amplios del EDM, Illeven Eleven muestra que el sonido también tuvo infraestructura duradera en otras ciudades. En ese sentido, el sello pertenece a un mapa más amplio de escenas regionales conectadas por DJs de gira, tiendas online y distribución digital.\n\nSu presencia continuada en internet sugiere un sello que ha seguido activo en algún sentido editorial, incluso cuando el mercado pasó de la cultura especializada guiada por el vinilo a las plataformas de descarga y la visibilidad de la era del streaming. Su actividad en espacios como SoundCloud, Beatport y redes sociales encaja con esa transición del modelo clásico de sello de breaks a una operación más flexible y digital.\n\nPara Optimal Breaks, Illeven Eleven destaca menos como institución mitificada que como sello de trabajo de la escena: uno de esos imprints que ayudaron a que el breakbeat estadounidense siguiera circulando después de su momento comercial más fuerte. Su valor está en la continuidad, la utilidad para DJs y su vínculo con artistas que siguieron comprometidos con la forma.\n\nPor eso, Illeven Eleven funciona como un buen punto de referencia para entender la cultura del breakbeat americano posterior a 2000: regional pero conectada, estilísticamente enfocada pero abierta a formas bass adyacentes, y construida alrededor de necesidades prácticas de la música de club más que de relatos de prestigio.",
  "image_url": null,
  "website": null,
  "key_artists": [
    "Keith Mackenzie",
    "DJ Fixx",
    "Sporty-O",
    "Whiskey Pete"
  ],
  "key_releases": [],
  "is_active": true,
  "is_featured": false
}
