{
  "slug": "mau5trap",
  "name": "mau5trap",
  "country": "Canada",
  "founded_year": 2007,
  "description_en": "mau5trap is the label platform built around deadmau5 and the wider orbit of artists connected to his studio aesthetic, DJ profile and crossover electronic audience. Although it is most commonly associated with progressive house, electro house and melodic techno, its catalogue has regularly touched adjacent bass, breaks and hybrid club forms rather than staying inside a single genre lane.\n\nThe imprint emerged in the late 2000s as deadmau5 moved from artist success into a more defined editorial role. In practice, mau5trap became both a home for his own releases and a channel for introducing producers whose music shared a taste for detailed sound design, widescreen arrangements and a polished, club-facing sense of scale.\n\nIts strongest historical identity sits in the 2010s, when the label became a recognizable name across digital stores, festival circuits and DJ culture. During that period, mau5trap helped formalize a particular strand of North American and international electronic music that sat between main-room visibility and producer-led listening culture.\n\nA key part of the label's profile has been its balance between headline releases and artist development. Alongside major deadmau5 records, it has hosted work by acts such as ATTLAS, No Mana, BlackGummy, Eekkoo and 1788-L, among others. That roster gave the imprint a broad but coherent range, from melodic and progressive material to darker, more mechanical and bass-weighted tracks.\n\nCompilation series have also been central to its identity. The We Are Friends volumes, in particular, functioned as annual or recurring snapshots of the label's extended network, offering a curated view of emerging names, stylistic shifts and the imprint's wider community rather than only its most visible headline acts.\n\nFor breakbeat listeners, mau5trap matters less as a pure breaks label than as a recurring meeting point between four-to-the-floor structures and broken-beat production logic. Parts of its catalogue, especially on compilations and selected artist releases, move through electro-breaks, syncopated bass programming and cinematic low-end design that connect with broader bass and breakbeat sensibilities.\n\nThat crossover quality is important to its place in electronic music history. mau5trap belongs to a generation of labels that treated genre borders more flexibly, allowing progressive house, electro, techno, halftime-inflected material and breakbeat-adjacent tracks to coexist under a strong visual and curatorial identity.\n\nThe label's public image has often been tied to deadmau5's authorship and brand power, but its longer-term significance lies in how it gave a durable platform to a network of producers working between club functionality and headphone detail. In that sense, it helped shape a recognizable post-EDM producer ecosystem without reducing itself to a single festival sound.\n\nIts release history spans singles, EPs, albums and compilations, with digital formats especially prominent, though some projects also appeared on vinyl. That format mix reflects the era in which the label rose: one where online distribution, DJ download culture and fan communities around specific producers were central to how electronic labels built identity.\n\nWithin the wider map of breakbeat and bass-adjacent culture, mau5trap is best understood as a neighboring institution rather than a scene-specific breaks imprint. Even so, its openness to broken rhythms, darker electro textures and technically detailed production has made parts of its catalogue relevant well beyond the progressive house audience with which it is most often associated.\n\nIts legacy is therefore not just a list of deadmau5 releases, but a broader editorial footprint: a label that connected big-room visibility, studio craft and a curated roster of producers who often operated in the spaces between established genre boxes. That breadth is what keeps mau5trap relevant in discussions of 2010s electronic music and its intersections with bass and breakbeat culture.",
  "description_es": "mau5trap es la plataforma discográfica articulada en torno a deadmau5 y a la órbita más amplia de artistas conectados con su estética de estudio, su perfil como DJ y su alcance dentro de la electrónica de cruce masivo. Aunque suele asociarse sobre todo con el progressive house, el electro house y ciertas zonas del techno melódico, su catálogo ha rozado con frecuencia formas adyacentes de bass, breaks y club híbrido en lugar de encerrarse en una sola línea de género.\n\nEl sello surgió a finales de los años 2000, cuando deadmau5 pasó del éxito como artista a un papel editorial más definido. En la práctica, mau5trap funcionó tanto como casa para sus propios lanzamientos como canal para presentar a productores cuya música compartía un gusto por el diseño sonoro minucioso, los arreglos de gran escala y una ambición claramente orientada a la pista.\n\nSu identidad histórica más fuerte se sitúa en la década de 2010, cuando el sello se convirtió en un nombre reconocible en tiendas digitales, circuitos de festivales y cultura DJ. En ese periodo, mau5trap ayudó a fijar una determinada corriente de música electrónica norteamericana e internacional situada entre la visibilidad de gran formato y una cultura de escucha más centrada en el productor.\n\nUna parte clave de su perfil ha sido el equilibrio entre lanzamientos de gran foco mediático y desarrollo de artistas. Junto a discos importantes de deadmau5, el sello publicó material de nombres como ATTLAS, No Mana, BlackGummy, Eekkoo y 1788-L, entre otros. Ese roster dio al imprint un rango amplio pero coherente, desde piezas melódicas y progresivas hasta cortes más oscuros, mecánicos y cargados de peso en graves.\n\nLas series de compilaciones también han sido centrales en su identidad. En particular, los volúmenes de We Are Friends funcionaron como instantáneas periódicas de la red extendida del sello, ofreciendo una visión curada de nuevos nombres, cambios estilísticos y de la comunidad más amplia del imprint, más allá de sus artistas más visibles.\n\nPara oyentes de breakbeat, mau5trap importa menos como sello de breaks en sentido estricto que como punto de encuentro recurrente entre estructuras four-to-the-floor y lógicas de producción de ritmo quebrado. Partes de su catálogo, sobre todo en compilaciones y en ciertos lanzamientos concretos, se mueven por terrenos de electro-breaks, programación sincopada de bajos y diseño cinematográfico de frecuencias graves que conectan con sensibilidades más amplias del bass y el breakbeat.\n\nEsa cualidad de cruce es importante para entender su lugar en la historia de la música electrónica. mau5trap pertenece a una generación de sellos que trató las fronteras de género con mayor flexibilidad, permitiendo que progressive house, electro, techno, material con pulso halftime y pistas cercanas al breakbeat convivieran bajo una identidad visual y curatorial fuerte.\n\nLa imagen pública del sello ha estado a menudo ligada a la autoría y al peso de marca de deadmau5, pero su importancia a largo plazo reside en cómo ofreció una plataforma duradera a una red de productores que trabajaban entre la funcionalidad de club y el detalle de escucha doméstica. En ese sentido, ayudó a dar forma a un ecosistema reconocible de productores posterior al boom EDM sin reducirse a un único sonido festivalero.\n\nSu historial de publicaciones abarca singles, EPs, álbumes y compilaciones, con especial protagonismo del formato digital, aunque algunos proyectos también aparecieron en vinilo. Esa mezcla de formatos refleja bien la época en la que el sello se consolidó: una en la que la distribución online, la cultura de descarga para DJs y las comunidades de seguidores alrededor de productores concretos eran centrales para construir identidad discográfica.\n\nDentro del mapa más amplio de la cultura breakbeat y bass adyacente, mau5trap se entiende mejor como una institución vecina que como un sello de breaks de escena específica. Aun así, su apertura a ritmos rotos, texturas electro más oscuras y una producción técnicamente detallada ha hecho que partes de su catálogo resulten relevantes mucho más allá del público con el que suele asociarse, el del progressive house.\n\nSu legado, por tanto, no es solo una lista de lanzamientos de deadmau5, sino una huella editorial más amplia: la de un sello que conectó visibilidad de gran escala, oficio de estudio y un roster curado de productores que a menudo operaban en los espacios entre categorías de género ya establecidas. Esa amplitud es lo que mantiene a mau5trap vigente en las conversaciones sobre la electrónica de los años 2010 y sus cruces con la cultura bass y breakbeat.",
  "image_url": null,
  "website": "https://mau5trap.bandcamp.com/music",
  "key_artists": [
    "deadmau5",
    "ATTLAS",
    "No Mana",
    "BlackGummy",
    "Eekkoo",
    "1788-L"
  ],
  "key_releases": [
    "deadmau5 - 4x4=12",
    "deadmau5 - Album Title Goes Here",
    "deadmau5 - while(1<2)",
    "ATTLAS - Siren",
    "1788-L - S Y N T H E T I K",
    "VA - We Are Friends",
    "VA - mau5trap Ten Year Anniversary",
    "VA - mau5trap '17"
  ],
  "is_active": true,
  "is_featured": true
}
